ecs_task.py
ecs_task-0.3.1.dist-info/LICENSE
ecs_task-0.3.1.dist-info/WHEEL
ecs_task-0.3.1.dist-info/METADATA
ecs_task-0.3.1.dist-info/RECORD
