Metadata-Version: 2.1
Name: ecs-task
Version: 0.3.1
Summary: Helper for registering new task definitions on AWS ECS and updating associated services.
Home-page: https://github.com/lincolnloop/ecs-task
License: UNKNOWN
Keywords: ecs,task,service,aws,container,deploy,rollback
Author: Peter Baumgartner
Author-email: pete@lincolnloop.com
Classifier: License :: OSI Approved :: MIT License
Classifier: Programming Language :: Python :: 2.7
Classifier: Programming Language :: Python :: 3
Requires-Dist: boto3
Requires-Dist: typing; python_version == '2.7'
Requires-Dist: pytest ; extra == "test"
Requires-Dist: pytest-cov ; extra == "test"
Requires-Dist: pytest-mock ; extra == "test"
Provides-Extra: test
